django_munin-0.2.2.dist-info/DESCRIPTION.rst
django_munin-0.2.2.dist-info/METADATA
django_munin-0.2.2.dist-info/RECORD
django_munin-0.2.2.dist-info/WHEEL
django_munin-0.2.2.dist-info/metadata.json
django_munin-0.2.2.dist-info/top_level.txt
munin/__init__.py
munin/helpers.py
munin/models.py
munin/urls.py
munin/views.py
