Metadata-Version: 2.0
Name: django-munin
Version: 0.2.2
Summary: Munin adaptor for Django
Home-page: http://github.com/ccnmtl/django-munin/
Author: Anders Pearson
Author-email: anders@columbia.edu
License: BSD
Platform: any
